Traffic_Light_Controller.v
`timescale 1ns/1ps


module Traffic_Light_Controller(

    input wire clk,
    input wire reset,
    output reg [2:0]light_M1,
    output reg [2:0]light_M2,
    output reg [2:0]light_MT,
    output reg [2:0]light_S
);

//defining states
parameter S1 = 3'b001;
parameter S2 = 3'b010;
parameter S3 = 3'b011;
parameter S4 = 3'b100;
parameter S5 = 3'b101;
parameter S6 = 3'b110;

reg [3:0]count;
reg [2:0]ps; //present state

//defining input times
parameter sec2 = 2; //TY
parameter sec3 = 3; //TSG
parameter sec5 = 5; //TTG
parameter sec7 = 7; //TMG

//state transitions
//here state is changed based on input
always @(posedge clk or posedge reset) begin
    if(reset) begin
        ps <= S1;
        count <= 0;
    end

    else begin
        
        case (ps)
            S1: if(count < sec7) begin
                    ps <= S1;
                    count <= count + 1;
                end

                else begin
                    ps <= S2;
                    count <= 0;
                end

            S2: if(count < sec2) begin
                    ps <= S2;
                    count <= count +1;
                end

                else begin
                    ps <= S3;
                    count <= 0;
                end

            S3: if(count < sec5) begin
                    ps <= S3;
                    count <= count + 1;
                end

                else begin
                    ps <= S4;
                    count <= 0;
                end

            S4: if(count < sec2) begin
                    ps <= S4;
                    count <= count +1;
                end

                else begin
                    ps <= S5;
                    count <= 0;
                end

            S5: if(count < sec3) begin
                    ps <= S5;
                    count <= count + 1;
                end

                else begin
                    ps <= S6;
                    count <= 0;
                end

            S6: if(count < sec2) begin
                    ps <= S6;
                    count <= count + 1;
                end

                else begin
                    ps <= S1;
                    count <= 0;
                end


            default: begin
                ps <= S1;
                count <= 0;
            end
            
                    
        endcase

        //display the current state and the count
        $display("State = %b, Count = %b", ps, count);
    end
end

//assigning lights
//here the outputs(lights) are changed based on the state
always @(ps) begin
    case (ps)
        S1: begin
            light_M1 <= 3'b001;
            light_M2 <= 3'b001;
            light_MT <= 3'b100;
            light_S <= 3'b100;
        end

        S2: begin
            light_M1 <= 3'b001;
            light_M2 <= 3'b010;
            light_MT <= 3'b100;
            light_S <= 3'b100;
        end

        S3: begin
            light_M1 <= 3'b001;
            light_M2 <= 3'b100;
            light_MT <= 3'b001;
            light_S <= 3'b100;
        end

        S4: begin
            light_M1 <= 3'b010;
            light_M2 <= 3'b100;
            light_MT <= 3'b010;
            light_S <= 3'b100;
        end

        S5: begin
            light_M1 <= 3'b100;
            light_M2 <= 3'b100;
            light_MT <= 3'b100;
            light_S <= 3'b001;
        end

        S6: begin
            light_M1 <= 3'b100;
            light_M2 <= 3'b100;
            light_MT <= 3'b100;
            light_S <= 3'b010;
        end

        default: begin
            light_M1 <= 3'b000;
            light_M2 <= 3'b000;
            light_MT <= 3'b000;
            light_S <= 3'b000;
        end
    endcase
end

endmodule

Traffic_Light_Controller_tb.v
`timescale 1ns/1ps
`include "Traffic_Light_Controller.v"

module Traffic_Light_Controller_tb();

reg clk;
reg reset;
wire [2:0]light_M1;
wire [2:0]light_M2;
wire [2:0]light_MT;
wire [2:0]light_S;

Traffic_Light_Controller dut(.clk(clk), .reset(reset), .light_M1(light_M1), .light_M2(light_M2), .light_MT(light_MT), .light_S(light_S));

//setting clock
initial begin
    clk = 0;
    forever #5 clk = ~clk;
end

initial begin
    reset = 0;
    #20; reset = 1;
    #20; reset = 0;
    #2000;

    $finish;
end

initial begin
    $dumpfile("dump.vcd");
    $dumpvars(0, Traffic_Light_Controller_tb);
end


endmodule

Three_Way_Traffic_Control/dump.vcd
$date
	Wed Jun 18 23:24:36 2025
$end
$version
	Icarus Verilog
$end
$timescale
	1ps
$end
$scope module Traffic_Light_Controller_tb $end
$var wire 3 ! light_S [2:0] $end
$var wire 3 " light_MT [2:0] $end
$var wire 3 # light_M2 [2:0] $end
$var wire 3 $ light_M1 [2:0] $end
$var reg 1 % clk $end
$var reg 1 & reset $end
$scope module dut $end
$var wire 1 % clk $end
$var wire 1 & reset $end
$var reg 4 ' count [3:0] $end
$var reg 3 ( light_M1 [2:0] $end
$var reg 3 ) light_M2 [2:0] $end
$var reg 3 * light_MT [2:0] $end
$var reg 3 + light_S [2:0] $end
$var reg 3 , ps [2:0] $end
$upscope $end
$upscope $end
$enddefinitions $end
#0
$dumpvars
bx ,
bx +
bx *
bx )
bx (
bx '
0&
0%
bx $
bx #
bx "
bx !
$end
#5000
b100 !
b100 +
b100 "
b100 *
b1 #
b1 )
b1 $
b1 (
b0 '
b0 ,
1%
#10000
0%
#15000
b1 '
1%
#20000
b0 '
0%
1&
#25000
1%
#30000
0%
#35000
1%
#40000
0%
0&
#45000
b1 '
1%
#50000
0%
#55000
b10 '
1%
#60000
0%
#65000
b11 '
1%
#70000
0%
#75000
b100 '
1%
#80000
0%
#85000
b101 '
1%
#90000
0%
#95000
b110 '
1%
#100000
0%
#105000
b111 '
1%
#110000
0%
#115000
b10 #
b10 )
b0 '
b1 ,
1%
#120000
0%
#125000
b1 '
1%
#130000
0%
#135000
b10 '
1%
#140000
0%
#145000
b1 "
b1 *
b100 #
b100 )
b0 '
b10 ,
1%
#150000
0%
#155000
b1 '
1%
#160000
0%
#165000
b10 '
1%
#170000
0%
#175000
b11 '
1%
#180000
0%
#185000
b100 '
1%
#190000
0%
#195000
b101 '
1%
#200000
0%
#205000
b10 "
b10 *
b10 $
b10 (
b0 '
b11 ,
1%
#210000
0%
#215000
b1 '
1%
#220000
0%
#225000
b10 '
1%
#230000
0%
#235000
b1 !
b1 +
b100 "
b100 *
b100 $
b100 (
b0 '
b100 ,
1%
#240000
0%
#245000
b1 '
1%
#250000
0%
#255000
b10 '
1%
#260000
0%
#265000
b11 '
1%
#270000
0%
#275000
b10 !
b10 +
b0 '
b101 ,
1%
#280000
0%
#285000
b1 '
1%
#290000
0%
#295000
b10 '
1%
#300000
0%
#305000
b100 !
b100 +
b1 #
b1 )
b1 $
b1 (
b0 '
b0 ,
1%
#310000
0%
#315000
b1 '
1%
#320000
0%
#325000
b10 '
1%
#330000
0%
#335000
b11 '
1%
#340000
0%
#345000
b100 '
1%
#350000
0%
#355000
b101 '
1%
#360000
0%
#365000
b110 '
1%
#370000
0%
#375000
b111 '
1%
#380000
0%
#385000
b10 #
b10 )
b0 '
b1 ,
1%
#390000
0%
#395000
b1 '
1%
#400000
0%
#405000
b10 '
1%
#410000
0%
#415000
b1 "
b1 *
b100 #
b100 )
b0 '
b10 ,
1%
#420000
0%
#425000
b1 '
1%
#430000
0%
#435000
b10 '
1%
#440000
0%
#445000
b11 '
1%
#450000
0%
#455000
b100 '
1%
#460000
0%
#465000
b101 '
1%
#470000
0%
#475000
b10 "
b10 *
b10 $
b10 (
b0 '
b11 ,
1%
#480000
0%
#485000
b1 '
1%
#490000
0%
#495000
b10 '
1%
#500000
0%
#505000
b1 !
b1 +
b100 "
b100 *
b100 $
b100 (
b0 '
b100 ,
1%
#510000
0%
#515000
b1 '
1%
#520000
0%
#525000
b10 '
1%
#530000
0%
#535000
b11 '
1%
#540000
0%
#545000
b10 !
b10 +
b0 '
b101 ,
1%
#550000
0%
#555000
b1 '
1%
#560000
0%
#565000
b10 '
1%
#570000
0%
#575000
b100 !
b100 +
b1 #
b1 )
b1 $
b1 (
b0 '
b0 ,
1%
#580000
0%
#585000
b1 '
1%
#590000
0%
#595000
b10 '
1%
#600000
0%
#605000
b11 '
1%
#610000
0%
#615000
b100 '
1%
#620000
0%
#625000
b101 '
1%
#630000
0%
#635000
b110 '
1%
#640000
0%
#645000
b111 '
1%
#650000
0%
#655000
b10 #
b10 )
b0 '
b1 ,
1%
#660000
0%
#665000
b1 '
1%
#670000
0%
#675000
b10 '
1%
#680000
0%
#685000
b1 "
b1 *
b100 #
b100 )
b0 '
b10 ,
1%
#690000
0%
#695000
b1 '
1%
#700000
0%
#705000
b10 '
1%
#710000
0%
#715000
b11 '
1%
#720000
0%
#725000
b100 '
1%
#730000
0%
#735000
b101 '
1%
#740000
0%
#745000
b10 "
b10 *
b10 $
b10 (
b0 '
b11 ,
1%
#750000
0%
#755000
b1 '
1%
#760000
0%
#765000
b10 '
1%
#770000
0%
#775000
b1 !
b1 +
b100 "
b100 *
b100 $
b100 (
b0 '
b100 ,
1%
#780000
0%
#785000
b1 '
1%
#790000
0%
#795000
b10 '
1%
#800000
0%
#805000
b11 '
1%
#810000
0%
#815000
b10 !
b10 +
b0 '
b101 ,
1%
#820000
0%
#825000
b1 '
1%
#830000
0%
#835000
b10 '
1%
#840000
0%
#845000
b100 !
b100 +
b1 #
b1 )
b1 $
b1 (
b0 '
b0 ,
1%
#850000
0%
#855000
b1 '
1%
#860000
0%
#865000
b10 '
1%
#870000
0%
#875000
b11 '
1%
#880000
0%
#885000
b100 '
1%
#890000
0%
#895000
b101 '
1%
#900000
0%
#905000
b110 '
1%
#910000
0%
#915000
b111 '
1%
#920000
0%
#925000
b10 #
b10 )
b0 '
b1 ,
1%
#930000
0%
#935000
b1 '
1%
#940000
0%
#945000
b10 '
1%
#950000
0%
#955000
b1 "
b1 *
b100 #
b100 )
b0 '
b10 ,
1%
#960000
0%
#965000
b1 '
1%
#970000
0%
#975000
b10 '
1%
#980000
0%
#985000
b11 '
1%
#990000
0%
#995000
b100 '
1%
#1000000
0%
#1005000
b101 '
1%
#1010000
0%
#1015000
b10 "
b10 *
b10 $
b10 (
b0 '
b11 ,
1%
#1020000
0%
#1025000
b1 '
1%
#1030000
0%
#1035000
b10 '
1%
#1040000
0%
#1045000
b1 !
b1 +
b100 "
b100 *
b100 $
b100 (
b0 '
b100 ,
1%
#1050000
0%
#1055000
b1 '
1%
#1060000
0%
#1065000
b10 '
1%
#1070000
0%
#1075000
b11 '
1%
#1080000
0%
#1085000
b10 !
b10 +
b0 '
b101 ,
1%
#1090000
0%
#1095000
b1 '
1%
#1100000
0%
#1105000
b10 '
1%
#1110000
0%
#1115000
b100 !
b100 +
b1 #
b1 )
b1 $
b1 (
b0 '
b0 ,
1%
#1120000
0%
#1125000
b1 '
1%
#1130000
0%
#1135000
b10 '
1%
#1140000
0%
#1145000
b11 '
1%
#1150000
0%
#1155000
b100 '
1%
#1160000
0%
#1165000
b101 '
1%
#1170000
0%
#1175000
b110 '
1%
#1180000
0%
#1185000
b111 '
1%
#1190000
0%
#1195000
b10 #
b10 )
b0 '
b1 ,
1%
#1200000
0%
#1205000
b1 '
1%
#1210000
0%
#1215000
b10 '
1%
#1220000
0%
#1225000
b1 "
b1 *
b100 #
b100 )
b0 '
b10 ,
1%
#1230000
0%
#1235000
b1 '
1%
#1240000
0%
#1245000
b10 '
1%
#1250000
0%
#1255000
b11 '
1%
#1260000
0%
#1265000
b100 '
1%
#1270000
0%
#1275000
b101 '
1%
#1280000
0%
#1285000
b10 "
b10 *
b10 $
b10 (
b0 '
b11 ,
1%
#1290000
0%
#1295000
b1 '
1%
#1300000
0%
#1305000
b10 '
1%
#1310000
0%
#1315000
b1 !
b1 +
b100 "
b100 *
b100 $
b100 (
b0 '
b100 ,
1%
#1320000
0%
#1325000
b1 '
1%
#1330000
0%
#1335000
b10 '
1%
#1340000
0%
#1345000
b11 '
1%
#1350000
0%
#1355000
b10 !
b10 +
b0 '
b101 ,
1%
#1360000
0%
#1365000
b1 '
1%
#1370000
0%
#1375000
b10 '
1%
#1380000
0%
#1385000
b100 !
b100 +
b1 #
b1 )
b1 $
b1 (
b0 '
b0 ,
1%
#1390000
0%
#1395000
b1 '
1%
#1400000
0%
#1405000
b10 '
1%
#1410000
0%
#1415000
b11 '
1%
#1420000
0%
#1425000
b100 '
1%
#1430000
0%
#1435000
b101 '
1%
#1440000
0%
#1445000
b110 '
1%
#1450000
0%
#1455000
b111 '
1%
#1460000
0%
#1465000
b10 #
b10 )
b0 '
b1 ,
1%
#1470000
0%
#1475000
b1 '
1%
#1480000
0%
#1485000
b10 '
1%
#1490000
0%
#1495000
b1 "
b1 *
b100 #
b100 )
b0 '
b10 ,
1%
#1500000
0%
#1505000
b1 '
1%
#1510000
0%
#1515000
b10 '
1%
#1520000
0%
#1525000
b11 '
1%
#1530000
0%
#1535000
b100 '
1%
#1540000
0%
#1545000
b101 '
1%
#1550000
0%
#1555000
b10 "
b10 *
b10 $
b10 (
b0 '
b11 ,
1%
#1560000
0%
#1565000
b1 '
1%
#1570000
0%
#1575000
b10 '
1%
#1580000
0%
#1585000
b1 !
b1 +
b100 "
b100 *
b100 $
b100 (
b0 '
b100 ,
1%
#1590000
0%
#1595000
b1 '
1%
#1600000
0%
#1605000
b10 '
1%
#1610000
0%
#1615000
b11 '
1%
#1620000
0%
#1625000
b10 !
b10 +
b0 '
b101 ,
1%
#1630000
0%
#1635000
b1 '
1%
#1640000
0%
#1645000
b10 '
1%
#1650000
0%
#1655000
b100 !
b100 +
b1 #
b1 )
b1 $
b1 (
b0 '
b0 ,
1%
#1660000
0%
#1665000
b1 '
1%
#1670000
0%
#1675000
b10 '
1%
#1680000
0%
#1685000
b11 '
1%
#1690000
0%
#1695000
b100 '
1%
#1700000
0%
#1705000
b101 '
1%
#1710000
0%
#1715000
b110 '
1%
#1720000
0%
#1725000
b111 '
1%
#1730000
0%
#1735000
b10 #
b10 )
b0 '
b1 ,
1%
#1740000
0%
#1745000
b1 '
1%
#1750000
0%
#1755000
b10 '
1%
#1760000
0%
#1765000
b1 "
b1 *
b100 #
b100 )
b0 '
b10 ,
1%
#1770000
0%
#1775000
b1 '
1%
#1780000
0%
#1785000
b10 '
1%
#1790000
0%
#1795000
b11 '
1%
#1800000
0%
#1805000
b100 '
1%
#1810000
0%
#1815000
b101 '
1%
#1820000
0%
#1825000
b10 "
b10 *
b10 $
b10 (
b0 '
b11 ,
1%
#1830000
0%
#1835000
b1 '
1%
#1840000
0%
#1845000
b10 '
1%
#1850000
0%
#1855000
b1 !
b1 +
b100 "
b100 *
b100 $
b100 (
b0 '
b100 ,
1%
#1860000
0%
#1865000
b1 '
1%
#1870000
0%
#1875000
b10 '
1%
#1880000
0%
#1885000
b11 '
1%
#1890000
0%
#1895000
b10 !
b10 +
b0 '
b101 ,
1%
#1900000
0%
#1905000
b1 '
1%
#1910000
0%
#1915000
b10 '
1%
#1920000
0%
#1925000
b100 !
b100 +
b1 #
b1 )
b1 $
b1 (
b0 '
b0 ,
1%
#1930000
0%
#1935000
b1 '
1%
#1940000
0%
#1945000
b10 '
1%
#1950000
0%
#1955000
b11 '
1%
#1960000
0%
#1965000
b100 '
1%
#1970000
0%
#1975000
b101 '
1%
#1980000
0%
#1985000
b110 '
1%
#1990000
0%
#1995000
b111 '
1%
#2000000
0%
#2005000
b10 #
b10 )
b0 '
b1 ,
1%
#2010000
0%
#2015000
b1 '
1%
#2020000
0%
#2025000
b10 '
1%
#2030000
0%
#2035000
b1 "
b1 *
b100 #
b100 )
b0 '
b10 ,
1%
